cyntrisec/__init__.py
cyntrisec/__main__.py
cyntrisec/aws/__init__.py
cyntrisec/aws/credentials.py
cyntrisec/aws/relationship_builder.py
cyntrisec/aws/scanner.py
cyntrisec/aws/collectors/__init__.py
cyntrisec/aws/collectors/ec2.py
cyntrisec/aws/collectors/iam.py
cyntrisec/aws/collectors/lambda_.py
cyntrisec/aws/collectors/network.py
cyntrisec/aws/collectors/rds.py
cyntrisec/aws/collectors/s3.py
cyntrisec/aws/collectors/usage.py
cyntrisec/aws/normalizers/__init__.py
cyntrisec/aws/normalizers/ec2.py
cyntrisec/aws/normalizers/iam.py
cyntrisec/aws/normalizers/lambda_.py
cyntrisec/aws/normalizers/network.py
cyntrisec/aws/normalizers/rds.py
cyntrisec/aws/normalizers/s3.py
cyntrisec/cli/__init__.py
cyntrisec/cli/analyze.py
cyntrisec/cli/ask.py
cyntrisec/cli/can.py
cyntrisec/cli/comply.py
cyntrisec/cli/cuts.py
cyntrisec/cli/diff.py
cyntrisec/cli/errors.py
cyntrisec/cli/explain.py
cyntrisec/cli/main.py
cyntrisec/cli/manifest.py
cyntrisec/cli/output.py
cyntrisec/cli/remediate.py
cyntrisec/cli/report.py
cyntrisec/cli/scan.py
cyntrisec/cli/schemas.py
cyntrisec/cli/serve.py
cyntrisec/cli/setup.py
cyntrisec/cli/validate.py
cyntrisec/cli/waste.py
cyntrisec/core/__init__.py
cyntrisec/core/business_config.py
cyntrisec/core/business_logic.py
cyntrisec/core/compliance.py
cyntrisec/core/cost_estimator.py
cyntrisec/core/cuts.py
cyntrisec/core/diff.py
cyntrisec/core/graph.py
cyntrisec/core/paths.py
cyntrisec/core/schema.py
cyntrisec/core/simulator.py
cyntrisec/core/waste.py
cyntrisec/mcp/__init__.py
cyntrisec/mcp/server.py
cyntrisec/storage/__init__.py
cyntrisec/storage/filesystem.py
cyntrisec/storage/memory.py
cyntrisec/storage/protocol.py
cyntrisec-0.1.9.dist-info/METADATA
cyntrisec-0.1.9.dist-info/WHEEL
cyntrisec-0.1.9.dist-info/entry_points.txt
cyntrisec-0.1.9.dist-info/licenses/LICENSE
cyntrisec-0.1.9.dist-info/licenses/NOTICE
cyntrisec-0.1.9.dist-info/RECORD
