Metadata-Version: 2.4
Name: cyntrisec
Version: 0.1.9
Summary: AWS capability graph analysis and attack path discovery CLI
Project-URL: Homepage, https://github.com/cyntrisec/cyntrisec-cli
Project-URL: Repository, https://github.com/cyntrisec/cyntrisec-cli
Project-URL: MCP Registry, https://registry.modelcontextprotocol.io
Author: CyntriSec
License:                                  Apache License
License-File: LICENSE
License-File: NOTICE
Keywords: attack-path,aws,cli,cost-optimization,mcp,mcp-server,security
Classifier: Development Status :: 3 - Alpha
Classifier: Environment :: Console
Classifier: Intended Audience :: Developers
Classifier: Intended Audience :: System Administrators
Classifier: License :: OSI Approved :: Apache Software License
Classifier: Operating System :: OS Independent
Classifier: Programming Language :: Python :: 3
Classifier: Programming Language :: Python :: 3.11
Classifier: Programming Language :: Python :: 3.12
Classifier: Topic :: Security
Requires-Python: >=3.11
Requires-Dist: boto3>=1.34
Requires-Dist: mcp>=1.0.0
Requires-Dist: pydantic>=2.4
Requires-Dist: pyyaml>=6.0
Requires-Dist: rich>=13.0
Requires-Dist: typer>=0.9.0
Provides-Extra: dev
Requires-Dist: hypothesis>=6.0; extra == 'dev'
Requires-Dist: moto>=5.0; extra == 'dev'
Requires-Dist: mypy>=1.0; extra == 'dev'
Requires-Dist: pytest-cov>=4.0; extra == 'dev'
Requires-Dist: pytest>=7.0; extra == 'dev'
Requires-Dist: ruff>=0.1; extra == 'dev'
Requires-Dist: types-pyyaml; extra == 'dev'
